LICENSE
README.md
pyfuzzymind/__init__.py
pyfuzzymind/pyfuzzymind.py
pyfuzzymind-0.1.2.dist-info/LICENSE
pyfuzzymind-0.1.2.dist-info/METADATA
pyfuzzymind-0.1.2.dist-info/WHEEL
pyfuzzymind-0.1.2.dist-info/RECORD
