Metadata-Version: 2.1
Name: pyfuzzymind
Version: 0.1.2
Summary: A Python library for implementing fuzzy logic systems, including fuzzy sets, fuzzy rules, inference engines, and various defuzzification methods.
Home-page: https://github.com/fadedreams/pyfuzzymind
License: MIT
Keywords: fuzzy,logic,fuzzy logic,fuzzy set,fuzzy rule,inference engine
Author: fadedreams7
Author-email: fadedreams7@gmail.com
Requires-Python: >=3.8,<4.0
Classifier: Environment :: Console
Classifier: License :: OSI Approved :: MIT License
Classifier: Operating System :: OS Independent
Classifier: Programming Language :: Python :: 3
Classifier: Programming Language :: Python :: 3.8
Classifier: Programming Language :: Python :: 3.9
Classifier: Programming Language :: Python :: 3.10
Classifier: Programming Language :: Python :: 3.11
Classifier: Programming Language :: Python :: 3.12
Classifier: Topic :: Utilities
Project-URL: Repository, https://github.com/fadedreams/pyfuzzymind
